hkp4py/__init__.py
hkp4py/client.py
hkp4py/utils.py
hkp4py-0.2.3.1.dist-info/LICENSE
hkp4py-0.2.3.1.dist-info/METADATA
hkp4py-0.2.3.1.dist-info/WHEEL
hkp4py-0.2.3.1.dist-info/top_level.txt
hkp4py-0.2.3.1.dist-info/RECORD
