Metadata-Version: 2.1
Name: hkp4py
Version: 0.2.3.1
Summary: A Library to get Keys from a keyserver specified
Home-page: https://github.com/Selfnet/hkp4py
Author: Marcel Fest
Author-email: marcelf@selfnet.de
License: MIT
Keywords: crypting keys gpg hkp hkps gnupg pgp keyserver
Platform: UNKNOWN
Classifier: Development Status :: 4 - Beta
Classifier: Intended Audience :: Developers
Classifier: License :: OSI Approved :: MIT License
Classifier: Topic :: Security :: Cryptography
Classifier: Programming Language :: Python :: 3
Classifier: Programming Language :: Python :: 2.6
Classifier: Programming Language :: Python :: 2.7
Provides-Extra: dev
